<map proto="1.4.2">
<name>BombBeach Bridge</name>
<version>2.0.0</version>
<created>2024-07-22</created>
<phase>development</phase>
<include id="towers-bridge"/>
<constants>
    <constant id="void-plane">0</constant>
</constants>
<maxbuildheight>17</maxbuildheight>
<authors>
    <author uuid="e5951644-77cd-40d0-85be-33594f0cae17"/> <!-- Alkaziaq -->
</authors>
<contributors>
    <contributor uuid="0cd8d8fe-8baf-4603-9ea3-4214283b9592" contribution="XML"/> <!-- nicolieeee -->
</contributors>
<spawns>
    <spawn team="blue-team" kit="spawn-kit" region="blue-spawn-point" yaw="90"/>
    <spawn team="red-team" kit="spawn-kit" region="red-spawn-point" yaw="-90"/>
    <default yaw="180">
        <regions>
            <point>0.5, 13, 0.5</point>
        </regions>
    </default>
</spawns>
<regions>
    <point id="blue-spawn-point">-24.5,17,0.5</point>
    <point id="red-spawn-point">25.5,17,0.5</point>
    <union id="spawns">
        <cuboid id="blue-scoreroom" min="-27,11,-2" max="-22,17,2"/>
        <cuboid id="red-scoreroom" min="23,11,-2" max="27,17,2"/>
        <cuboid id="sky" min="-36,16,-oo" max="19,oo,oo"/>
    </union>
    <union id="scoreboxes">
        <cuboid id="blue-scorebox" min="-27,11,-2" max="-23,11.5,2"/>
        <cuboid id="red-scorebox" min="23,11,-2" max="27,11.5,2"/>
    </union>
    <union id="secondfloor">
        <cuboid min="-3,19,-oo" max="4,oo,oo"/>
    </union>
    <apply region="secondfloor" kit="kill"/>
    <union id="map-boundaries">
        <negative><rectangle min="-37,-20" max="37,20"/></negative>
    </union>
</regions>
<portals pitch="@0">
    <portal filter="only-red" region="blue-scorebox" destination="red-spawn-point" yaw="@90" observers="never"/>
    <portal filter="only-blue" region="red-scorebox" destination="blue-spawn-point" yaw="@-90" observers="never"/>
</portals>
</map>